existutil/__init__.py
existutil-0.0.0a0.dist-info/LICENSE
existutil-0.0.0a0.dist-info/METADATA
existutil-0.0.0a0.dist-info/WHEEL
existutil-0.0.0a0.dist-info/top_level.txt
existutil-0.0.0a0.dist-info/RECORD
